Reuters/__init__.py
Reuters-1.2.1.dist-info/LICENSE
Reuters-1.2.1.dist-info/METADATA
Reuters-1.2.1.dist-info/WHEEL
Reuters-1.2.1.dist-info/top_level.txt
Reuters-1.2.1.dist-info/RECORD
