Metadata-Version: 2.1
Name: Reuters
Version: 1.2.1
Summary: Reuters ticker information retriever for Python
Home-page: https://github.com/HurinHu/Reuters
Author: Hurin Hu
Author-email: hurin@live.ca
License: UNKNOWN
Platform: UNKNOWN
Classifier: Programming Language :: Python :: 3.6
Classifier: License :: OSI Approved :: MIT License
Classifier: Operating System :: OS Independent
License-File: LICENSE
Requires-Dist: beautifulsoup4
Requires-Dist: requests
